elefanto_drf_exceptions/__init__.py
elefanto_drf_exceptions/formatter.py
elefanto_drf_exceptions/handler.py
elefanto_drf_exceptions/types.py
elefanto_drf_exceptions-0.1.0.dist-info/METADATA
elefanto_drf_exceptions-0.1.0.dist-info/WHEEL
elefanto_drf_exceptions-0.1.0.dist-info/RECORD
