Metadata-Version: 2.1
Name: elefanto-drf-exceptions
Version: 0.1.0
Summary: 
Author: Zhanibek
Author-email: rzhanik@gmail.com
Requires-Python: >=3.10,<4.0
Classifier: Programming Language :: Python :: 3
Classifier: Programming Language :: Python :: 3.10
Classifier: Programming Language :: Python :: 3.11
Requires-Dist: django (>=4.2.1,<5.0.0)
Requires-Dist: djangorestframework (>=3.14.0,<4.0.0)
Requires-Dist: drf-standardized-errors (>=0.12.5,<0.13.0)
